voicesynth/__init__.py
voicesynth/exceptions.py
voicesynth/models.py
voicesynth/voicesynth.py
voicesynth-0.2.3.dist-info/LICENSE
voicesynth-0.2.3.dist-info/METADATA
voicesynth-0.2.3.dist-info/WHEEL
voicesynth-0.2.3.dist-info/top_level.txt
voicesynth-0.2.3.dist-info/RECORD
