Metadata-Version: 2.1
Name: voicesynth
Version: 0.2.3
Summary: Package for realistic voice synthesis
Author: ilyamiro
Author-email: ilyamiro.work@gmail.com
Classifier: Programming Language :: Python :: 3
Classifier: License :: OSI Approved :: Apache Software License
Classifier: Operating System :: OS Independent
Classifier: Development Status :: 3 - Alpha
License-File: LICENSE
Requires-Dist: numpy
Requires-Dist: playsound
